pyrusapix/__init__.py
pyrusapix/authenticator.py
pyrusapix/catalog.py
pyrusapix/exceptions.py
pyrusapix/extractor.py
pyrusapix/files.py
pyrusapix/forms.py
pyrusapix/tasks.py
pyrusapix-1.2.dist-info/METADATA
pyrusapix-1.2.dist-info/WHEEL
pyrusapix-1.2.dist-info/RECORD
