Metadata-Version: 2.4
Name: pyrusapix
Version: 1.2
Summary: Альтернативная библиотека для работы с Pyrus API
Author-email: Майкл Белачев <mbelachev@yandex.ru>
Requires-Python: >=3.7
Requires-Dist: aiohttp
Requires-Dist: python-dotenv
